setup.py
text_comparer/__init__.py
text_comparer/similarity.py
text_comparer/vectorizer.py
text_comparer.egg-info/PKG-INFO
text_comparer.egg-info/SOURCES.txt
text_comparer.egg-info/dependency_links.txt
text_comparer.egg-info/top_level.txt