Metadata-Version: 1.1
Name: text-comparer
Version: 0.0.2
Summary: Metric for comparing text
Home-page: https://github.com/sergeio/text_comparer
Author: Sergei Orlov
Author-email: UNKNOWN
License: BSD
Platform: UNKNOWN
Classifier: Development Status :: 2 - Pre-Alpha
Classifier: Intended Audience :: Developers
Classifier: License :: OSI Approved :: BSD License
Classifier: Operating System :: MacOS :: MacOS X
Classifier: Operating System :: POSIX
Classifier: Programming Language :: Python
